verbm/__init__.py
verbm/__main__.py
verbm/clap.py
verbm/init.py
verbm/py.typed
verbm/run.py
verbm/source.py
verbm/version.py
verbm/config/__init__.py
verbm/config/config.py
verbm/config/version_control.py
verbm/version_control/README.md
verbm/version_control/__init__.py
verbm/version_control/call.py
verbm/version_control/git.py
verbm/version_control/interface.py
verbm-1.0.0.dist-info/METADATA
verbm-1.0.0.dist-info/WHEEL
verbm-1.0.0.dist-info/entry_points.txt
verbm-1.0.0.dist-info/licenses/LICENSE
verbm-1.0.0.dist-info/RECORD
