Metadata-Version: 2.4
Name: verbm
Version: 1.0.0
Summary: Language agnostic version bump tool
Project-URL: Homepage, https://github.com/chocolacula/verbm
Author-email: Maxim Voloshin <mvolloshin@gmail.com>
License: Apache License (2.0)
License-File: LICENSE
Classifier: License :: OSI Approved :: Apache Software License
Classifier: Programming Language :: Python :: 3
Requires-Python: >=3.9
Requires-Dist: pydantic
Requires-Dist: pyyaml
